icemu/__init__.py
icemu/chip.py
icemu/counters.py
icemu/decoders.py
icemu/gates.py
icemu/mcu.py
icemu/pin.py
icemu/seg7.py
icemu/shiftregisters.py
icemu/sim.py
icemu/ui.py
icemu/util.py
icemu-0.4.0.dist-info/DESCRIPTION.rst
icemu-0.4.0.dist-info/METADATA
icemu-0.4.0.dist-info/RECORD
icemu-0.4.0.dist-info/WHEEL
icemu-0.4.0.dist-info/metadata.json
icemu-0.4.0.dist-info/top_level.txt
