Metadata-Version: 2.0
Name: icemu
Version: 0.4.0
Summary: Emulate Integrated Circuits
Home-page: https://github.com/hsoft/icemu
Author: Virgil Dupras
Author-email: hsoft@hardcoded.net
License: LGPLv3
Platform: UNKNOWN
Classifier: Development Status :: 3 - Alpha
Classifier: Intended Audience :: Developers
Classifier: License :: OSI Approved :: GNU Lesser General Public License v3 (LGPLv3)
Classifier: Programming Language :: Python :: 3
Classifier: Programming Language :: Python :: 3.4
Classifier: Programming Language :: Python :: 3.5
Classifier: Programming Language :: Python :: 3.6
Classifier: Topic :: Software Development :: Embedded Systems
Classifier: Topic :: System :: Emulators
